MANIFEST.in
setup.py
docs/requirements.txt
proso/__init__.py
proso/conversion.py
proso/dict.py
proso/func.py
proso/list.py
proso/rand.py
proso/reflection.py
proso/release.py
proso/svg.py
proso/test_reflection.py
proso/time.py
proso/django/__init__.py
proso/django/auth.py
proso/django/cache.py
proso/django/config.py
proso/django/db.py
proso/django/enrichment.py
proso/django/log.py
proso/django/models.py
proso/django/request.py
proso/django/response.py
proso/django/test.py
proso/django/test_request.py
proso/models/__init__.py
proso/models/context.py
proso/models/environment.py
proso/models/item_selection.py
proso/models/option_selection.py
proso/models/prediction.py
proso/models/test_environment.py
proso/models/test_option_selection.py
proso_apps.egg-info/PKG-INFO
proso_apps.egg-info/SOURCES.txt
proso_apps.egg-info/dependency_links.txt
proso_apps.egg-info/namespace_packages.txt
proso_apps.egg-info/requires.txt
proso_apps.egg-info/top_level.txt
proso_common/__init__.py
proso_common/api_test.py
proso_common/apps.py
proso_common/config_test.py
proso_common/context_processors.py
proso_common/json_enrich.py
proso_common/middleware.py
proso_common/models.py
proso_common/urls.py
proso_common/views.py
proso_common/management/__init__.py
proso_common/management/commands/__init__.py
proso_common/management/commands/answers2events.py
proso_common/management/commands/custom_export.py
proso_common/management/commands/integrity_check.py
proso_common/management/commands/load_global_custom_config.py
proso_common/management/commands/push_events.py
proso_common/management/commands/table2csv.py
proso_common/migrations/0001_initial.py
proso_common/migrations/0002_auto_global_custom_config.py
proso_common/migrations/__init__.py
proso_common/static/proso_common/pure-min.css
proso_common/static/proso_common/side-menu.css
proso_common/static/proso_common/angular/angular-cookies.min.js
proso_common/static/proso_common/angular/angular-cookies.min.js.map
proso_common/static/proso_common/angular/angular-mocks.js
proso_common/static/proso_common/angular/angular.min.js
proso_common/static/proso_common/angular/angular.min.js.map
proso_common/templates/base.html
proso_common/templates/common_base.html
