Metadata-Version: 1.0
Name: proso-apps
Version: 3.21.1
Summary: General library for applications in PROSO projects
Home-page: https://github.com/adaptive-learning/proso-apps
Author: Adaptive Learning Group
Author-email: al@fi.muni.cz
License: MIT
Platform: UNKNOWN
